news-gong-try/__init__.py
news-gong-try/tools/__init__.py
news-gong-try/tools/test.py
news_gong_try/__init__.py
news_gong_try/tools/__init__.py
news_gong_try/tools/test.py
news_gong_try-0.4.dist-info/METADATA
news_gong_try-0.4.dist-info/WHEEL
news_gong_try-0.4.dist-info/top_level.txt
news_gong_try-0.4.dist-info/RECORD
