Metadata-Version: 2.1
Name: news-gong-try
Version: 0.4
Summary: UNKNOWN
Home-page: https://gitee.com/gongzhengyang/gong.git
Author: gongzhengyang
Author-email: UNKNOWN
License: UNKNOWN
Platform: UNKNOWN
Requires-Dist: requests
